gplpy/__init__.py
gplpy/evo/__init__.py
gplpy/evo/evolution.py
gplpy/evo/log.py
gplpy/gggp/__init__.py
gplpy/gggp/derivation.py
gplpy/gggp/grammar.py
gplpy/gggp/metaderivation.py
gplpy-1.1.0.2.dist-info/LICENSE
gplpy-1.1.0.2.dist-info/METADATA
gplpy-1.1.0.2.dist-info/WHEEL
gplpy-1.1.0.2.dist-info/top_level.txt
gplpy-1.1.0.2.dist-info/RECORD
