Metadata-Version: 2.1
Name: gplpy
Version: 1.1.0.2
Summary: Grammar-Guided Genetic Programming Library
Home-page: https://github.com/aturing/GPLpy.git
Author: aturing
Author-email: itic@aturing.com
License: Apache License 2.0
Platform: UNKNOWN
Requires-Python: >=3.6
Requires-Dist: numpy
Requires-Dist: scipy
Requires-Dist: pandas
Requires-Dist: matplotlib
Requires-Dist: pymongo[srv]
